condor_assistant/__init__.py
condor_assistant-1.3.data/scripts/example.py
condor_assistant-1.3.dist-info/LICENSE
condor_assistant-1.3.dist-info/METADATA
condor_assistant-1.3.dist-info/WHEEL
condor_assistant-1.3.dist-info/top_level.txt
condor_assistant-1.3.dist-info/RECORD
