Metadata-Version: 2.1
Name: condor_assistant
Version: 1.3
Summary: Handy tool for condor submission
Home-page: https://github.com/qwerasd903/condor_assistant
Author: Jay Chan
Author-email: jay.chan@cern.ch
License: MIT
Platform: UNKNOWN
License-File: LICENSE
